ImagePRO/__init__.py
ImagePRO/human_analysis/__init__.py
ImagePRO/human_analysis/body_analysis/__init__.py
ImagePRO/human_analysis/body_analysis/body_pose_estimation.py
ImagePRO/human_analysis/body_analysis/hand_tracking.py
ImagePRO/human_analysis/face_analysis/__init__.py
ImagePRO/human_analysis/face_analysis/eye_status_analysis.py
ImagePRO/human_analysis/face_analysis/face_comparison.py
ImagePRO/human_analysis/face_analysis/face_detection.py
ImagePRO/human_analysis/face_analysis/face_mesh_analysis.py
ImagePRO/human_analysis/face_analysis/head_pose_estimation.py
ImagePRO/object_analysis/__init__.py
ImagePRO/object_analysis/object_detection.py
ImagePRO/pre_processing/__init__.py
ImagePRO/pre_processing/blur.py
ImagePRO/pre_processing/contrast.py
ImagePRO/pre_processing/crop.py
ImagePRO/pre_processing/dataset_generator.py
ImagePRO/pre_processing/grayscale.py
ImagePRO/pre_processing/histogram.py
ImagePRO/pre_processing/resize.py
ImagePRO/pre_processing/rotate.py
ImagePRO/pre_processing/sharpen.py
ImagePRO/utils/__init__.py
ImagePRO/utils/image.py
ImagePRO/utils/result.py
imagepro_python-1.2.0.dist-info/licenses/LICENSE
imagepro_python-1.2.0.dist-info/METADATA
imagepro_python-1.2.0.dist-info/WHEEL
imagepro_python-1.2.0.dist-info/top_level.txt
imagepro_python-1.2.0.dist-info/RECORD
