Metadata-Version: 2.4
Name: ImagePRO-Python
Version: 1.2.0
Summary: Professional & modular image processing library with OpenCV, MediaPipe, and YOLO integration.
Author-email: Parsa Safaie <parsasafaie.2568@proton.me>
License: MIT
Project-URL: Homepage, https://github.com/parsasafaie/ImagePRO
Project-URL: Repository, https://github.com/parsasafaie/ImagePRO.git
Project-URL: Documentation, https://github.com/parsasafaie/ImagePRO#readme
Project-URL: Issues, https://github.com/parsasafaie/ImagePRO/issues
Keywords: opencv,mediapipe,computer-vision,face,pose,yolo,image-processing
Classifier: Development Status :: 4 - Beta
Classifier: Intended Audience :: Developers
Classifier: Intended Audience :: Science/Research
Classifier: Programming Language :: Python :: 3
Classifier: Programming Language :: Python :: 3.9
Classifier: Programming Language :: Python :: 3.10
Classifier: Programming Language :: Python :: 3.11
Classifier: Programming Language :: Python :: 3.12
Classifier: Programming Language :: Python :: 3.13
Classifier: License :: OSI Approved :: MIT License
Classifier: Operating System :: OS Independent
Classifier: Topic :: Scientific/Engineering :: Image Processing
Classifier: Topic :: Scientific/Engineering :: Artificial Intelligence
Classifier: Topic :: Software Development :: Libraries :: Python Modules
Requires-Python: <3.13,>=3.9
License-File: LICENSE
Requires-Dist: numpy<3.0,>=1.24
Requires-Dist: opencv-python<6.0,>=4.8
Requires-Dist: matplotlib<4.0,>=3.7
Provides-Extra: yolo
Requires-Dist: ultralytics<10.0,>=8.2; extra == "yolo"
Provides-Extra: mediapipe
Requires-Dist: mediapipe<1.0,>=0.10; extra == "mediapipe"
Provides-Extra: insightface
Requires-Dist: insightface<1.0,>=0.7; extra == "insightface"
Requires-Dist: onnxruntime<3.0,>=1.16; extra == "insightface"
Provides-Extra: full
Requires-Dist: mediapipe<1.0,>=0.10; extra == "full"
Requires-Dist: ultralytics<10.0,>=8.2; extra == "full"
Requires-Dist: insightface<1.0,>=0.7; extra == "full"
Requires-Dist: onnxruntime<3.0,>=1.16; extra == "full"
Dynamic: license-file
